pynotiq_client/__init__.py
pynotiq_client/config.py
pynotiq_client/queue_manager.py
pynotiq_client/queue_manager_new.py
pynotiq_client/remote_queue.py
pynotiq_client-0.7.0.dist-info/METADATA
pynotiq_client-0.7.0.dist-info/WHEEL
pynotiq_client-0.7.0.dist-info/top_level.txt
pynotiq_client-0.7.0.dist-info/RECORD
