Metadata-Version: 2.4
Name: pynotiq_client
Version: 0.7.0
Summary: Python client library for adding messages to PyNotiQ queue with local and remote support
Home-page: https://github.com/downlevel/pynotiq_client
Author: Your Name
Classifier: Programming Language :: Python :: 3
Classifier: License :: OSI Approved :: MIT License
Classifier: Operating System :: OS Independent
Requires-Python: >=3.6
Requires-Dist: requests>=2.25.0
Requires-Dist: urllib3>=1.26.0
Dynamic: author
Dynamic: classifier
Dynamic: description
Dynamic: description-content-type
Dynamic: home-page
Dynamic: requires-dist
Dynamic: requires-python
Dynamic: summary
